{
  "type": "witchery:distillery_crafting",
  "altarPower": 5,
  "cookingTime": 100,
  "inputItems": [
    {
      "count": 1,
      "id": "witchery:breath_of_the_goddess"
    },
    {
      "count": 1,
      "id": "minecraft:lapis_lazuli"
    }
  ],
  "jarConsumption": 3,
  "outputItems": [
    {
      "count": 1,
      "id": "witchery:tear_of_the_goddess"
    },
    {
      "count": 1,
      "id": "witchery:whiff_of_magic"
    },
    {
      "count": 1,
      "id": "minecraft:slime_ball"
    },
    {
      "count": 1,
      "id": "witchery:foul_fume"
    }
  ]
}